superlance/__init__.py
superlance/compat.py
superlance/crashmail.py
superlance/crashmailbatch.py
superlance/crashsms.py
superlance/fatalmailbatch.py
superlance/grower.py
superlance/httpok.py
superlance/memmon.py
superlance/process_state_email_monitor.py
superlance/process_state_monitor.py
superlance/timeoutconn.py
superlance/tests/__init__.py
superlance/tests/crashmail_test.py
superlance/tests/crashmailbatch_test.py
superlance/tests/crashsms_test.py
superlance/tests/dummy.py
superlance/tests/fatalmailbatch_test.py
superlance/tests/httpok_test.py
superlance/tests/memmon_test.py
superlance/tests/process_state_email_monitor_test.py
superlance/tests/process_state_monitor_test.py
superlance/tests/test_crashmail.py
superlance/tests/test_crashmailbatch.py
superlance/tests/test_crashsms.py
superlance/tests/test_fatalmailbatch.py
superlance/tests/test_httpok.py
superlance/tests/test_memmon.py
superlance/tests/test_process_state_email_monitor.py
superlance/tests/test_process_state_monitor.py
superlance-2.0.0.dist-info/LICENSE.txt
superlance-2.0.0.dist-info/METADATA
superlance-2.0.0.dist-info/WHEEL
superlance-2.0.0.dist-info/entry_points.txt
superlance-2.0.0.dist-info/top_level.txt
superlance-2.0.0.dist-info/RECORD
